NullPlus/__init__.py
nullplus-1.1.1.dist-info/licenses/LICENSE
nullplus-1.1.1.dist-info/METADATA
nullplus-1.1.1.dist-info/WHEEL
nullplus-1.1.1.dist-info/top_level.txt
nullplus-1.1.1.dist-info/RECORD
