Metadata-Version: 2.4
Name: NullPlus
Version: 1.1.1
Summary: A simple class that allows for error handling and eating inputs
Author-email: StrawberryMilcRivers <chocomilccy@gmail.com>
License-Expression: MIT
Requires-Python: >=3.8
License-File: LICENSE
Dynamic: license-file
